{
  "select": {
    "text": {
      "font": {
        "family": {
          "$value": "{text.fontFamily}",
          "$type": "fontFamilies"
        },
        "size": {
          "$value": "{font.size.small}",
          "$type": "dimension"
        },
        "weight": {
          "$value": "{font.weight.medium}",
          "$type": "dimension"
        }
      },
      "lineHeight": {
        "$value": "{font.lineHeight.default}",
        "$type": "dimension"
      },
      "letterSpacing": {
        "$value": "{font.letterSpacing.pos.medium}",
        "$type": "dimension"
      },
      "color": {
        "default": {
          "$value": "{framer.color.text.default}",
          "$type": "color"
        },
        "disabled": {
          "$value": "{framer.color.text.tertiary}",
          "$type": "color"
        }
      }
    },
    "status": {
      "gap": {
        "$value": "{size.pos.xxsmall}",
        "$type": "dimension"
      },
      "height": {
        "$value": "{size.pos.medium}",
        "$type": "dimension"
      }
    },
    "checkbox": {
      "height": {
        "$value": "{size.pos.medium}",
        "$type": "dimension"
      },
      "gap": {
        "$value": "{size.pos.xmsmall}",
        "$type": "dimension"
      }
    },
    "box": {
      "height": {
        "$value": "{size.pos.xmsmall}",
        "$type": "dimension"
      },
      "width": {
        "$value": "{size.pos.xmsmall}",
        "$type": "dimension"
      },
      "radius": {
        "$value": "{border.radius.small}",
        "$type": "dimension"
      },
      "border": {
        "default": {
          "width": {
            "$value": "{size.null}",
            "$type": "dimension"
          },
          "color": {
            "$value": "{grey.transparent}",
            "$type": "color"
          }
        },
        "checked": {
          "default": {
            "width": {
              "$value": "{size.null}",
              "$type": "dimension"
            },
            "color": {
              "$value": "{grey.transparent}",
              "$type": "color"
            }
          },
          "disabled": {
            "width": {
              "$value": "{size.null}",
              "$type": "dimension"
            },
            "color": {
              "$value": "{grey.transparent}",
              "$type": "color"
            }
          }
        },
        "disabled": {
          "width": {
            "$value": "{size.null}",
            "$type": "dimension"
          },
          "color": {
            "$value": "{grey.transparent}",
            "$type": "color"
          }
        },
        "secondary": {
          "color": {
            "default": {
              "$value": "{grey.transparent}",
              "$type": "color"
            },
            "focus": {
              "$value": "{framer.color.tint.default}",
              "$type": "color"
            },
            "checked": {
              "focus": {
                "$value": "{framer.color.tint.extraDark}",
                "$type": "color"
              }
            }
          },
          "width": {
            "default": {
              "$value": "{size.null}",
              "$type": "dimension"
            },
            "focus": {
              "$value": "{size.pos.unit}",
              "$type": "dimension"
            },
            "checked": {
              "focus": {
                "$value": "{size.pos.unit}",
                "$type": "dimension"
              }
            }
          },
          "offset": {
            "default": {
              "$value": "{size.null}",
              "$type": "dimension"
            },
            "focus": {
              "$value": "{size.neg.unit}",
              "$type": "dimension"
            },
            "checked": {
              "focus": {
                "$value": "{size.neg.unit}",
                "$type": "dimension"
              }
            }
          }
        }
      },
      "background": {
        "color": {
          "default": {
            "$value": "{framer.color.bg.tertiary}",
            "$type": "color"
          },
          "checked": {
            "default": {
              "$value": "{framer.color.tint.default}",
              "$type": "color"
            },
            "disabled": {
              "$value": "{framer.color.bg.secondary}",
              "$type": "color"
            }
          },
          "disabled": {
            "$value": "{framer.color.bg.secondary}",
            "$type": "color"
          }
        }
      },
      "tick": {
        "icon": {
          "$value": "{icon.check}",
          "$type": "link"
        },
        "position": {
          "top": {
            "$value": "{size.neg.xxxsmall}",
            "$type": "dimension"
          },
          "left": {
            "$value": "{size.neg.xxxsmall}",
            "$type": "dimension"
          }
        },
        "width": {
          "$value": "{size.pos.msmall}",
          "$type": "dimension"
        },
        "height": {
          "$value": "{size.pos.msmall}",
          "$type": "dimension"
        },
        "color": {
          "default": {
            "$value": "{framer.color.text.reversed}",
            "$type": "color"
          },
          "disabled": {
            "$value": "{framer.color.text.tertiary}",
            "$type": "color"
          }
        }
      }
    },
    "switch": {
      "height": {
        "$value": "{size.pos.medium}",
        "$type": "dimension"
      },
      "gap": {
        "$value": "{size.pos.xmsmall}",
        "$type": "dimension"
      }
    },
    "toggle": {
      "height": {
        "$value": "{size.pos.xsmall}",
        "$type": "dimension"
      },
      "width": {
        "$value": "{size.pos.small}",
        "$type": "dimension"
      },
      "radius": {
        "$value": "{size.pos.xsmall}",
        "$type": "dimension"
      },
      "background": {
        "color": {
          "default": {
            "$value": "{framer.color.bg.tertiary}",
            "$type": "color"
          },
          "checked": {
            "default": {
              "$value": "{framer.color.tint.default}",
              "$type": "color"
            },
            "disabled": {
              "$value": "{framer.color.bg.secondary}",
              "$type": "color"
            }
          },
          "disabled": {
            "$value": "{framer.color.bg.secondary}",
            "$type": "color"
          }
        }
      },
      "border": {
        "default": {
          "width": {
            "$value": "{size.null}",
            "$type": "dimension"
          },
          "color": {
            "$value": "{grey.transparent}",
            "$type": "color"
          }
        },
        "checked": {
          "default": {
            "width": {
              "$value": "{size.null}",
              "$type": "dimension"
            },
            "color": {
              "$value": "{grey.transparent}",
              "$type": "color"
            }
          },
          "disabled": {
            "width": {
              "$value": "{size.null}",
              "$type": "dimension"
            },
            "color": {
              "$value": "{grey.transparent}",
              "$type": "color"
            }
          }
        },
        "disabled": {
          "width": {
            "$value": "{size.null}",
            "$type": "dimension"
          },
          "color": {
            "$value": "{grey.transparent}",
            "$type": "color"
          }
        },
        "secondary": {
          "color": {
            "default": {
              "$value": "{grey.transparent}",
              "$type": "color"
            },
            "focus": {
              "$value": "{framer.color.tint.default}",
              "$type": "color"
            },
            "checked": {
              "focus": {
                "$value": "{framer.color.tint.extraDark}",
                "$type": "color"
              }
            }
          },
          "width": {
            "default": {
              "$value": "{size.null}",
              "$type": "dimension"
            },
            "focus": {
              "$value": "{size.pos.unit}",
              "$type": "dimension"
            },
            "checked": {
              "focus": {
                "$value": "{size.pos.unit}",
                "$type": "dimension"
              }
            }
          },
          "offset": {
            "default": {
              "$value": "{size.null}",
              "$type": "dimension"
            },
            "focus": {
              "$value": "{size.neg.unit}",
              "$type": "dimension"
            },
            "checked": {
              "focus": {
                "$value": "{size.neg.unit}",
                "$type": "dimension"
              }
            }
          }
        }
      },
      "transition": {
        "$value": "background-color 0.2s ease-in-out",
        "$type": "string"
      },
      "knob": {
        "height": {
          "$value": "{size.pos.xmsmall}",
          "$type": "dimension"
        },
        "width": {
          "$value": "{size.pos.xmsmall}",
          "$type": "dimension"
        },
        "radius": {
          "$value": "{border.radius.full}",
          "$type": "dimension"
        },
        "left": {
          "$value": "11px",
          "$type": "dimension"
        },
        "background": {
          "color": {
            "default": {
              "$value": "{framer.color.text.reversed}",
              "$type": "color"
            },
            "checked": {
              "default": {
                "$value": "{framer.color.text.reversed}",
                "$type": "color"
              },
              "disabled": {
                "$value": "{framer.color.text.tertiary}",
                "$type": "color"
              }
            },
            "disabled": {
              "$value": "{framer.color.text.tertiary}",
              "$type": "color"
            }
          }
        },
        "transform": {
          "default": {
            "translateX": {
              "$value": "{size.pos.xunit}",
              "$type": "dimension"
            },
            "translateY": {
              "$value": "{size.pos.xunit}",
              "$type": "dimension"
            }
          },
          "checked": {
            "translateX": {
              "$value": "10px",
              "$type": "dimension"
            },
            "translateY": {
              "$value": "{size.pos.xunit}",
              "$type": "dimension"
            }
          }
        },
        "transition": {
          "backgroundColor": {
            "$value": {
              "duration": "200ms",
              "timingFunction": [0.37, 0, 0.63, 1]
            },
            "$type": "transition"
          },
          "transform": {
            "$value": {
              "duration": "200ms",
              "timingFunction": [0.37, 0, 0.63, 1]
            },
            "$type": "transition"
          }
        }
      }
    },
    "radio": {
      "height": {
        "$value": "{size.pos.medium}",
        "$type": "dimension"
      },
      "gap": {
        "$value": "{size.pos.xmsmall}",
        "$type": "dimension"
      }
    },
    "button": {
      "height": {
        "$value": "{size.pos.xsmall}",
        "$type": "dimension"
      },
      "width": {
        "$value": "{size.pos.xsmall}",
        "$type": "dimension"
      },
      "inner": {
        "height": {
          "$value": "6px",
          "$type": "dimension"
        },
        "width": {
          "$value": "6px",
          "$type": "dimension"
        },
        "position": {
          "top": {
            "$value": "5px",
            "$type": "dimension"
          },
          "left": {
            "$value": "5px",
            "$type": "dimension"
          }
        }
      },
      "radius": {
        "$value": "{border.radius.full}",
        "$type": "dimension"
      },
      "icon": {
        "color": {
          "default": {
            "$value": "{framer.color.text.reversed}",
            "$type": "color"
          },
          "disabled": {
            "$value": "{framer.color.text.tertiary}",
            "$type": "color"
          }
        }
      },
      "background": {
        "color": {
          "default": {
            "$value": "{framer.color.bg.tertiary}",
            "$type": "color"
          },
          "checked": {
            "default": {
              "$value": "{framer.color.tint.default}",
              "$type": "color"
            },
            "disabled": {
              "$value": "{framer.color.bg.secondary}",
              "$type": "color"
            }
          },
          "disabled": {
            "$value": "{framer.color.bg.secondary}",
            "$type": "color"
          }
        }
      },
      "border": {
        "default": {
          "width": {
            "$value": "{size.null}",
            "$type": "dimension"
          },
          "color": {
            "$value": "{grey.transparent}",
            "$type": "color"
          }
        },
        "checked": {
          "default": {
            "width": {
              "$value": "{size.null}",
              "$type": "dimension"
            },
            "color": {
              "$value": "{grey.transparent}",
              "$type": "color"
            }
          },
          "disabled": {
            "width": {
              "$value": "{size.null}",
              "$type": "dimension"
            },
            "color": {
              "$value": "{grey.transparent}",
              "$type": "color"
            }
          }
        },
        "disabled": {
          "width": {
            "$value": "{size.null}",
            "$type": "dimension"
          },
          "color": {
            "$value": "{grey.transparent}",
            "$type": "color"
          }
        },
        "secondary": {
          "color": {
            "default": {
              "$value": "{grey.transparent}",
              "$type": "color"
            },
            "focus": {
              "$value": "{framer.color.tint.default}",
              "$type": "color"
            },
            "checked": {
              "focus": {
                "$value": "{framer.color.tint.extraDark}",
                "$type": "color"
              }
            }
          },
          "width": {
            "default": {
              "$value": "{size.null}",
              "$type": "dimension"
            },
            "focus": {
              "$value": "{size.pos.unit}",
              "$type": "dimension"
            },
            "checked": {
              "focus": {
                "$value": "{size.pos.unit}",
                "$type": "dimension"
              }
            }
          },
          "offset": {
            "default": {
              "$value": "{size.null}",
              "$type": "dimension"
            },
            "focus": {
              "$value": "{size.neg.unit}",
              "$type": "dimension"
            },
            "checked": {
              "focus": {
                "$value": "{size.neg.unit}",
                "$type": "dimension"
              }
            }
          }
        }
      }
    }
  }
}
